LICENSE
MANIFEST.in
README.md
VERSION
pyproject.toml
setup.py
periflow_cli.egg-info/PKG-INFO
periflow_cli.egg-info/SOURCES.txt
periflow_cli.egg-info/dependency_links.txt
periflow_cli.egg-info/entry_points.txt
periflow_cli.egg-info/requires.txt
periflow_cli.egg-info/top_level.txt
pfcli/__init__.py
pfcli/artifact.py
pfcli/billing.py
pfcli/checkpoint.py
pfcli/context.py
pfcli/credential.py
pfcli/dataset.py
pfcli/deployment.py
pfcli/group.py
pfcli/job.py
pfcli/key.py
pfcli/main.py
pfcli/project.py
pfcli/vm.py
pfcli/configurator/__init__.py
pfcli/configurator/base.py
pfcli/configurator/credential.py
pfcli/configurator/data.py
pfcli/configurator/deployment.py
pfcli/configurator/job.py
pfcli/service/__init__.py
pfcli/service/auth.py
pfcli/service/cloud.py
pfcli/service/formatter.py
pfcli/service/client/__init__.py
pfcli/service/client/base.py
pfcli/service/client/billing.py
pfcli/service/client/checkpoint.py
pfcli/service/client/credential.py
pfcli/service/client/data.py
pfcli/service/client/deployment.py
pfcli/service/client/file.py
pfcli/service/client/group.py
pfcli/service/client/job.py
pfcli/service/client/metrics.py
pfcli/service/client/project.py
pfcli/service/client/user.py
pfcli/utils/__init__.py
pfcli/utils/format.py
pfcli/utils/fs.py
pfcli/utils/prompt.py
pfcli/utils/request.py
pfcli/utils/testing.py
pfcli/utils/url.py
pfcli/utils/validate.py
pfcli/utils/version.py
test/test_utils.py