Metadata-Version: 2.1
Name: periflow-cli
Version: 0.1.18
Summary: PeriFlow CLI
Home-page: https://github.com/friendliai/periflow-cli
Author: FriendliAI
License: Apache License 2.0
Classifier: Programming Language :: Python :: 3
Classifier: Natural Language :: English
Requires-Python: >=3.8
Provides-Extra: test
Provides-Extra: dev
License-File: LICENSE
